brython_dragdrop/__init__.py
brython_dragdrop/api.py
brython_dragdrop-0.1.0.dist-info/LICENSE
brython_dragdrop-0.1.0.dist-info/METADATA
brython_dragdrop-0.1.0.dist-info/WHEEL
brython_dragdrop-0.1.0.dist-info/top_level.txt
brython_dragdrop-0.1.0.dist-info/RECORD
