Metadata-Version: 2.1
Name: brython-dragdrop
Version: 0.1.0
Summary: My package description
Home-page: https://github.com/rayluo/brython.dragdrop
Author: Ray Luo
Author-email: rayluo.mba@gmail.com
License: MIT
Project-URL: Changelog, https://github.com/rayluo/brython.dragdrop/releases
Keywords: brython,drag,drop
Classifier: Development Status :: 4 - Beta
Classifier: License :: OSI Approved :: MIT License
Classifier: Operating System :: OS Independent
Classifier: Programming Language :: Python
Classifier: Programming Language :: Python :: 3 :: Only
Classifier: Programming Language :: Python :: 3
Classifier: Programming Language :: Python :: 3.7
Classifier: Programming Language :: Python :: 3.8
Classifier: Programming Language :: Python :: 3.9
Classifier: Programming Language :: Python :: 3.10
Classifier: Programming Language :: Python :: 3.11
Classifier: Programming Language :: Python :: 3.12
License-File: LICENSE
